Workbook

Sheet Returns & Asset Mix assumption
C6: This workbook along with all its contents are the intellectual property of The 1% Club, distribution of which is strictly prohibited.
C10: Entry cells
C11: Formula cells
D12: < 3 years | E12: 3-5 years | F12: > 6 years
B13: Asset class | C13: Expected returns | D13: Short Term | E13: Medium Term | F13: Long Term
B14: Domestic equity | C14: 0.12 | D14: 0 | E14: 0.4 | F14: 0.6
B15: US equity | C15: 0.12 | D15: 0 | E15: 0 | F15: 0.1
B16: Debt | C16: 0.06 | D16: 1 | E16: 0.5 | F16: 0.15
B17: Gold (SGB / ETF) | C17: 0.06 | D17: 0 | E17: 0.1 | F17: 0.05
B18: Crypto | C18: 0.2 | D18: 0 | E18: 0 | F18: 0.05
B19: Real Estate / REITs | C19: 0.1 | D19: 0 | E19: 0 | F19: 0.05
B20: Effective returns | D20: =SUMPRODUCT($C$14:$C$19,D14:D19) -> 0.06 | E20: =SUMPRODUCT(E14:E19,$C$14:$C$19)*0.4+D20*0.6 -> 0.0696 | F20: =SUMPRODUCT(F14:F19,C14:C19) -> 0.111

Sheet Cash flows
B6: This workbook along with all its contents are the intellectual property of The 1% Club, distribution of which is strictly prohibited.
C9: Entry cells
C10: Formula cells
B12: Inflows | C12: Value (INR)
B13: Post-tax salary | C13: 175000
B14: Business income | C14: 10000
B15: Rental income
B16: Others | C16: 1000
B17: Total | C17: =SUM(C13:C16) -> 186000
B19: Outflows | C19: Value (INR)
B20: Monthly expenses | C20: 53000
B21: Compulsory investments (eg. ULIPs, chit funds etc.) | C21: 36500
B22: Loan EMIs | C22: 46000
B23: Insurance premiums | C23: 13000
B24: Others | C24: 20000
B25: Total | C25: =SUM(C20:C24) -> 168500
B27: Investing surplus | C27: =C17-C25 -> 17500

Sheet Net worth
C6: Entry cells
C7: Formula cells | E7: This workbook along with all its contents are the intellectual property of The 1% Club, distribution of which is strictly prohibited.
B9: Total Net Worth | C9: =C34-C44 -> 7111629
B10: Liquid Assets | C10: =C33 -> 380230
B12: Assets | E12: Total Asset Summary | I12: Current Investable Asset Allocation | M12: Required Investable Asset Allocation
B13: Particulars | C13: Value (INR) | E13: Particulars | F13: Value (INR) | G13: % contribution | I13: Particulars | J13: Value (INR) | K13: % contribution | M13: Particulars | N13: Value (INR) | O13: % contribution
B14: Illiquid | E14: Real Estate / Reits | F14: =C15+C16+C32 -> 12000000 | G14: =IFERROR(F14/$F$20,0) -> 0.92698237 | I14: Real Estate / Reits | J14: =C32+C16 -> 3000000 | K14: =IFERROR(J14/$J$20,0) -> 0.82299334 | M14: Real Estate / REITs | N14: =SUMIF('Financial Goals'!$E$11:$E$25,"Short Term",'Financial Goals'!$G$11:$G$25)*VLOOKUP('Net worth'!$M14,'Returns & Asset Mix assumption'!$B$13:$F$19,3,0)+SUMIF('Financial Goals'!$E$11:$E$25,"Medium Term",'Financial Goals'!$G$11:$G$25)*VLOOKUP('Net worth'!$M14,'Returns & Asset Mix assumption'!$B$13:$F$19,4,0)+SUMIF('Financial Goals'!$E$11:$E$25,"Long Term",'Financial Goals'!$G$11:$G$25)*VLOOKUP('Net worth'!$M14,'Returns & Asset Mix assumption'!$B$13:$F$19,5,0) -> 12750 | O14: =IFERROR(N14/$N$20,0) -> 0.023507894
B15: Home | C15: ='Real estate & REIT'!C11 -> 9000000 | E15: Domestic Equity | F15: =C25+C26+C19+C28 -> 99226 | G15: =IFERROR(F15/$F$20,0) -> 0.0076650627 | I15: Domestic Equity | J15: =C25+C26+C28+C19 -> 99226 | K15: =IFERROR(J15/$J$20,0) -> 0.027220779 | M15: Domestic Equity | N15: =SUMIF('Financial Goals'!$E$11:$E$25,"Short Term",'Financial Goals'!$G$11:$G$25)*VLOOKUP('Net worth'!$M15,'Returns & Asset Mix assumption'!$B$13:$F$19,3,0)+SUMIF('Financial Goals'!$E$11:$E$25,"Medium Term",'Financial Goals'!$G$11:$G$25)*VLOOKUP('Net worth'!$M15,'Returns & Asset Mix assumption'!$B$13:$F$19,4,0)+SUMIF('Financial Goals'!$E$11:$E$25,"Long Term",'Financial Goals'!$G$11:$G$25)*VLOOKUP('Net worth'!$M15,'Returns & Asset Mix assumption'!$B$13:$F$19,5,0) -> 153000 | O15: =IFERROR(N15/$N$20,0) -> 0.28209473
B16: Other real estate | C16: ='Real estate & REIT'!C12 -> 3000000 | E16: US Equity | F16: =SUM(C27:C27) -> 0 | G16: =IFERROR(F16/$F$20,0) -> 0 | I16: US Equity | J16: =C27 -> 0 | K16: =IFERROR(J16/$J$20,0) -> 0 | M16: US equity | N16: =SUMIF('Financial Goals'!$E$11:$E$25,"Short Term",'Financial Goals'!$G$11:$G$25)*VLOOKUP('Net worth'!$M16,'Returns & Asset Mix assumption'!$B$13:$F$19,3,0)+SUMIF('Financial Goals'!$E$11:$E$25,"Medium Term",'Financial Goals'!$G$11:$G$25)*VLOOKUP('Net worth'!$M16,'Returns & Asset Mix assumption'!$B$13:$F$19,4,0)+SUMIF('Financial Goals'!$E$11:$E$25,"Long Term",'Financial Goals'!$G$11:$G$25)*VLOOKUP('Net worth'!$M16,'Returns & Asset Mix assumption'!$B$13:$F$19,5,0) -> 25500 | O16: =IFERROR(N16/$N$20,0) -> 0.047015788
B17: Jewellery | C17: =Gold!C11 -> 300000 | E17: Debt | F17: =SUM(C23:C24)+C20+C29 -> 513135 | G17: =IFERROR(F17/$F$20,0) -> 0.039638925 | I17: Debt | J17: =C23+C24+C29+C20 -> 513135 | K17: =IFERROR(J17/$J$20,0) -> 0.1407689 | M17: Debt | N17: =SUMIF('Financial Goals'!$E$11:$E$25,"Short Term",'Financial Goals'!$G$11:$G$25)*VLOOKUP('Net worth'!$M17,'Returns & Asset Mix assumption'!$B$13:$F$19,3,0)+SUMIF('Financial Goals'!$E$11:$E$25,"Medium Term",'Financial Goals'!$G$11:$G$25)*VLOOKUP('Net worth'!$M17,'Returns & Asset Mix assumption'!$B$13:$F$19,4,0)+SUMIF('Financial Goals'!$E$11:$E$25,"Long Term",'Financial Goals'!$G$11:$G$25)*VLOOKUP('Net worth'!$M17,'Returns & Asset Mix assumption'!$B$13:$F$19,5,0) -> 325621 | O17: =IFERROR(N17/$N$20,0) -> 0.6003658
B18: SGB | C18: =Gold!C12 -> 10000 | E18: Gold | F18: =C17+C18+C30 -> 317869 | G18: =IFERROR(F18/$F$20,0) -> 0.024554913 | I18: Gold | J18: =C30+C18 -> 17869 | K18: =IFERROR(J18/$J$20,0) -> 0.0049020226 | M18: Gold (SGB / ETF) | N18: =SUMIF('Financial Goals'!$E$11:$E$25,"Short Term",'Financial Goals'!$G$11:$G$25)*VLOOKUP('Net worth'!$M18,'Returns & Asset Mix assumption'!$B$13:$F$19,3,0)+SUMIF('Financial Goals'!$E$11:$E$25,"Medium Term",'Financial Goals'!$G$11:$G$25)*VLOOKUP('Net worth'!$M18,'Returns & Asset Mix assumption'!$B$13:$F$19,4,0)+SUMIF('Financial Goals'!$E$11:$E$25,"Long Term",'Financial Goals'!$G$11:$G$25)*VLOOKUP('Net worth'!$M18,'Returns & Asset Mix assumption'!$B$13:$F$19,5,0) -> 12750 | O18: =IFERROR(N18/$N$20,0) -> 0.023507894
B19: ULIPs | C19: =Miscellaneous!C13 -> 0 | E19: Crypto | F19: =C31 -> 15000 | G19: =IFERROR(F19/$F$20,0) -> 0.001158728 | I19: Crypto | J19: =C31 -> 15000 | K19: =IFERROR(J19/$J$20,0) -> 0.0041149667 | M19: Crypto | N19: =SUMIF('Financial Goals'!$E$11:$E$25,"Short Term",'Financial Goals'!$G$11:$G$25)*VLOOKUP('Net worth'!$M19,'Returns & Asset Mix assumption'!$B$13:$F$19,3,0)+SUMIF('Financial Goals'!$E$11:$E$25,"Medium Term",'Financial Goals'!$G$11:$G$25)*VLOOKUP('Net worth'!$M19,'Returns & Asset Mix assumption'!$B$13:$F$19,4,0)+SUMIF('Financial Goals'!$E$11:$E$25,"Long Term",'Financial Goals'!$G$11:$G$25)*VLOOKUP('Net worth'!$M19,'Returns & Asset Mix assumption'!$B$13:$F$19,5,0) -> 12750 | O19: =IFERROR(N19/$N$20,0) -> 0.023507894
B20: EPF / PPF / VPF | C20: =Debt!L15 -> 255000 | E20: Total | F20: =SUM(F14:F19) -> 12945230 | G20: =SUM(G14:G19) -> 1 | I20: Total | J20: =SUM(J14:J19) -> 3645230 | K20: =SUM(K14:K19) -> 1 | M20: Total | N20: =SUM(N14:N19) -> 542371 | O20: =SUM(O14:O19) -> 1
B21: Total Illiquid | C21: =SUM(C15:C20) -> 12565000
B22: Liquid
B23: Fixed deposit | C23: =Debt!F15 -> 0
B24: Debt funds | C24: =Debt!I15 -> 32779
B25: Domestic Stock market | C25: ='Domestic Equity'!C24 -> 0
B26: Domestic Equity mutual funds | C26: ='Domestic Equity'!G25 -> 99226
B27: US Equity | C27: ='US equity'!C15 -> 0
B28: Small case | C28: =Miscellaneous!C14 -> 0
B29: Liquid (savings account, cash, liquid fund) | C29: =Debt!C15 -> 225356 | D29: ='Cash flows'!C25*6&" recommended" -> 1011000 recommended
B30: Gold ETF, digital gold etc | C30: =Gold!C13 -> 7869
B31: Crypto | C31: =Crypto!C14 -> 15000
B32: REITs | C32: ='Real estate & REIT'!C13 -> 0
B33: Total Liquid | C33: =SUM(C23:C32) -> 380230
B34: Total Assets | C34: =C21+C33 -> 12945230
B36: Liabilities
B37: Particulars | C37: Value (INR)
B38: Home loan | C38: =5519347+143254 -> 5662601
B39: Education loan
B40: Car loan | C40: 15000
B41: Personal/Gold loan
B42: Credit card | C42: 0
B43: Other liabilities | C43: 156000
B44: Total Liabilities | C44: =SUM(C38:C43) -> 5833601

Sheet Real estate & REIT
B4: This workbook along with all its contents are the intellectual property of The 1% Club, distribution of which is strictly prohibited.
C7: Input cells
C8: Formula cells
B10: Particulars | C10: Value (INR)
B11: Home | C11: 9000000
B12: Other real estate | C12: 3000000
B13: REITs | D13: Best REITs in India
B14: Total | C14: =IFERROR(C13+C12+C11,0) -> 12000000

Sheet Domestic Equity
C5: Input cells
C6: Formula cells (you cannot edit)
B20: Company size | C20: Current value (INR) | D20: Contribution % | F20: Mutual fund components | G20: Current value (INR) | H20: Contribution % | K20: Mutual fund components | L20: Current value (INR) | M20: Contribution %
B21: Largecap | C21: =SUMIF($C$28:$C$1048576,"Largecap",$D$28:$D$1048576) -> 0 | D21: =IFERROR(C21/$C$24,0) -> 0 | F21: Largecap | G21: =SUMIFS($H$28:$H$405,$G$28:$G$405,F21) -> 0 | H21: =IFERROR(G21/$G$25,0) -> 0 | K21: Largecap | L21: =SUMIFS($M$28:$M$405,$L$28:$L$405,K21) -> 0 | M21: =IFERROR(L21/$L$25,0) -> 0 | O21: Age | P21: 20-30 | Q21: 30-45 | R21: 45-65 | S21: >65
B22: Midcap | C22: =SUMIF($C$28:$C$1048576,"Midcap",$D$28:$D$1048576) -> 0 | D22: =IFERROR(C22/$C$24,0) -> 0 | F22: Midcap | G22: =SUMIFS($H$28:$H$405,$G$28:$G$405,F22) -> 36524 | H22: =IFERROR(G22/$G$25,0) -> 0.36808901 | K22: Midcap | L22: =SUMIFS($M$28:$M$405,$L$28:$L$405,K22) -> 0 | M22: =IFERROR(L22/$L$25,0) -> 0 | O22: Largecap | P22: 0.2 | Q22: 0.3 | R22: 0.4 | S22: 0.6
B23: Smallcap | C23: =SUMIF($C$28:$C$1048576,"Smallcap",$D$28:$D$1048576) -> 0 | D23: =IFERROR(C23/$C$24,0) -> 0 | F23: Smallcap | G23: =SUMIFS($H$28:$H$405,$G$28:$G$405,F23) -> 0 | H23: =IFERROR(G23/$G$25,0) -> 0 | K23: Smallcap | L23: =SUMIFS($M$28:$M$405,$L$28:$L$405,K23) -> 0 | M23: =IFERROR(L23/$L$25,0) -> 0 | O23: Midcap | P23: 0.3 | Q23: 0.2 | R23: 0.2 | S23: 0.2
B24: Total | C24: =SUM(C21:C23) -> 0 | D24: =SUM(D21:D23) -> 0 | F24: Flexi/Multi cap | G24: =SUMIFS($H$28:$H$405,$G$28:$G$405,F24) -> 62702 | H24: =IFERROR(G24/$G$25,0) -> 0.63191099 | K24: Flexi/Multi cap | L24: =SUMIFS($M$28:$M$405,$L$28:$L$405,K24) -> 4000 | M24: =IFERROR(L24/$L$25,0) -> 1 | O24: Smallcap | P24: 0.2 | Q24: 0.2 | R24: 0.1 | S24: -2.7755576e-17
F25: Total | G25: =SUM(G21:G24) -> 99226 | H25: =SUM(H21:H24) -> 1 | K25: Total | L25: =SUM(L21:L24) -> 4000 | M25: =SUM(M21:M24) -> 1 | O25: Flexi/Multicap | P25: 0.3 | Q25: 0.3 | R25: 0.3 | S25: 0.2
B27: Stocks | C27: Category | D27: Current Value (INR) | F27: Mutual fund / ETF / Smallcase | G27: Category | H27: Current Value (INR) | K27: Mutual fund / ETF / Smallcase / Stock | L27: Category | M27: SIP | N27: Max
F28: Parag Parikh Equity | G28: Flexi/Multi cap | H28: 62702 | K28: Parag Parikh Equity | L28: Flexi/Multi cap | M28: 4000 | N28: ='Financial Goals'!M27 -> 4500
F29: Aditya Birla Sun Life PSU | G29: MidCap | H29: 25631 | N29: =IF(L25>N28,"You don't have enough money","")
F30: Quant ELSS TAX Saver Fund Direct Growth | G30: MidCap | H30: 10893

Sheet US equity
B5: This workbook along with all its contents are the intellectual property of The 1% Club, distribution of which is strictly prohibited.
C8: Input cells
C9: Formula cells (you cannot edit)
B11: Particulars | C11: Value (INR)
B12: S&P500 ETF
B13: Other ETFs
B14: US Mutual funds
B15: Total | C15: =SUM(C12:C14) -> 0

Sheet Debt
P2: SIP Allocator
C4: Input cells
C5: Formula cells (you cannot edit) | H5: This workbook along with all its contents are the intellectual property of The 1% Club, distribution of which is strictly prohibited.
O11: Mutual fund components | P11: Current value (INR) | Q11: Contribution % | R11: Required contribution
O12: FD/RD/Arbitrage | P12: =SUMIFS($Q$18:$Q$1051,$P$18:$P$1051,O12) -> 26000 | Q12: =P12/$P$15 -> 0.9122807 | R12: =IFERROR(SUMIFS('Financial Goals'!$O$11:$O$25,'Financial Goals'!$E$11:$E$25,"Short Term")/R18,0) -> 0.97087379
O13: Banking PSUs/Corporate funds | P13: =SUMIFS($Q$18:$Q$1051,$P$18:$P$1051,O13) -> 0 | Q13: =P13/$P$15 -> 0 | R13: =IFERROR(SUMIFS('Financial Goals'!$O$11:$O$25,'Financial Goals'!$E$11:$E$25,"Medium Term")/R18,0) -> 0
O14: Government securities/Equity Saver funds | P14: =SUMIFS($Q$18:$Q$1051,$P$18:$P$1051,O14) -> 2500 | Q14: =P14/$P$15 -> 0.087719298 | R14: =IFERROR(SUMIFS('Financial Goals'!$O$11:$O$25,'Financial Goals'!$E$11:$E$25,"Long Term")/R18,0) -> 0.029126214
B15: Liquid | C15: =SUM(C18:C1048576) -> 225356 | E15: Fixed Deposit | F15: =SUM(F18:F1048576) -> 0 | H15: Debt funds | I15: =SUM(I18:I1048576) -> 32779 | K15: Government investments | L15: =SUM(L18:L1048576) -> 255000 | O15: Total | P15: =SUM(P12:P14) -> 28500 | Q15: =SUM(Q12:Q14) -> 1 | R15: =SUM(R12:R14) -> 1
B17: Particulars | C17: Current Value (INR) | E17: Bank name | F17: Current Value (INR) | H17: Name | I17: Current Value (INR) | K17: Name | L17: Current Value (INR) | O17: Mutual fund / ETF / Smallcase / Stock | P17: Duration | Q17: SIP | R17: Max
B18: Cash | C18: 50000 | H18: Wint Bond | I18: 32779 | K18: NPS | L18: 5000 | O18: Bank of Baroda Savings Account | P18: FD/RD/Arbitrage | Q18: 20000 | R18: ='Financial Goals'!O27 -> 38625 | V18: FD/RD/Arbitrage
B19: Mahima BOB Account | C19: 134371 | K19: EPF | L19: 250000 | R19: =IF(P15>R18,"You are over investing into Debt","") | V19: Banking PSUs/Corporate funds
B20: HDFC Bank Salary | C20: 15000 | O20: PF | P20: Government securities/Equity Saver funds | Q20: 2500 | V20: Government securities/Equity Saver funds
B21: SBI Bank | C21: 1597 | O21: ICICI iWish for Scooty | P21: FD/RD/Arbitrage | Q21: 6000
B22: Standard Chartered | C22: 1339
B23: BOB Current Account | C23: 12587
B24: Bank of Maharashtra | C24: 5040
B25: BOB Savings | C25: 1688
B26: Bajaj Finserve Liquid Fund | C26: 2
B27: ICICI Prudential Liquid Fund | C27: 3732

Sheet Gold
B4: This workbook along with all its contents are the intellectual property of The 1% Club, distribution of which is strictly prohibited.
C7: Input cells
C8: Formula cells (you cannot edit)
B10: Particulars | C10: Value (INR)
B11: Jewellery | C11: 300000
B12: SGB | C12: 10000
B13: Gold ETF / Digital gold | C13: 7869
B14: Total | C14: =SUM(C11:C13) -> 317869

Sheet Crypto
B6: This workbook along with all its contents are the intellectual property of The 1% Club, distribution of which is strictly prohibited.
C9: Input cells
C10: Formula cells (you cannot edit)
B12: Particulars | C12: Value (INR)
B13: Crypto | C13: 15000
B14: Total | C14: =SUM(C13) -> 15000

Sheet Miscellaneous
B6: This workbook along with all its contents are the intellectual property of The 1% Club, distribution of which is strictly prohibited.
C9: Input cells
C10: Formula cells (you cannot edit)
B12: Particulars | C12: Value (INR)
B13: ULIPs/other insurance products
B14: Small Case
B15: Total | C15: =SUM(C13) -> 0

Sheet Financial Goals
D6: This workbook along with all its contents are the intellectual property of The 1% Club, distribution of which is strictly prohibited.
C7: Input cells
C8: Formula cells | M8: SIP Asset allocation
B10: Goal | C10: Priority | D10: Time (Years left for goal) | E10: Goal Type | F10: Amount required (today) | G10: Amount available (today) | H10: Goal inflation | I10: Amount required (future) | J10: Step up | K10: SIP required | M10: Domestic equity | N10: US equity | O10: Debt | P10: Gold | Q10: Crypto | R10: Real Estate / REITs
B11: Close the plot loan | C11: 1 | D11: 1 | E11: =IF(ISBLANK(D11)=TRUE,"",IF(D11<3,"Short Term",IF(D11<=6,"Medium Term","Long Term"))) -> Short Term | F11: 156317 | G11: 41000 | H11: 0.096 | I11: =IFERROR(IF(F11=G11," ",F11*(1+H11)^D11-G11*(1+HLOOKUP(E11,'Returns & Asset Mix assumption'!$D$13:$F$20,8,0))^D11),"") -> 127863.43 | J11: 0.05 | K11: 10000 | M11: =IFERROR(HLOOKUP($E11,'Returns & Asset Mix assumption'!$D$13:$F$20,2,0)*$K11,0) -> 0 | N11: =IFERROR(HLOOKUP($E11,'Returns & Asset Mix assumption'!$D$13:$F$20,3,0)*$K11,0) -> 0 | O11: =IFERROR(HLOOKUP($E11,'Returns & Asset Mix assumption'!$D$13:$F$20,4,0)*$K11,0) -> 10000 | P11: =IFERROR(HLOOKUP($E11,'Returns & Asset Mix assumption'!$D$13:$F$20,5,0)*$K11,0) -> 0 | Q11: =IFERROR(HLOOKUP($E11,'Returns & Asset Mix assumption'!$D$13:$F$20,6,0)*$K11,0) -> 0 | R11: =IFERROR(HLOOKUP($E11,'Returns & Asset Mix assumption'!$D$13:$F$20,7,0)*$K11,0) -> 0
B12: Emergency Fund | C12: 1 | D12: 1 | E12: =IF(ISBLANK(D12)=TRUE,"",IF(D12<3,"Short Term",IF(D12<=6,"Medium Term","Long Term"))) -> Short Term | F12: 300000 | G12: =114371+50000+82000 -> 246371 | H12: 0.01 | I12: =IFERROR(IF(F12=G12," ",F12*(1+H12)^D12-G12*(1+HLOOKUP(E12,'Returns & Asset Mix assumption'!$D$13:$F$20,8,0))^D12),"") -> 41846.74 | J12: 0.05 | K12: 4000 | M12: =IFERROR(HLOOKUP($E12,'Returns & Asset Mix assumption'!$D$13:$F$20,2,0)*$K12,0) -> 0 | N12: =IFERROR(HLOOKUP($E12,'Returns & Asset Mix assumption'!$D$13:$F$20,3,0)*$K12,0) -> 0 | O12: =IFERROR(HLOOKUP($E12,'Returns & Asset Mix assumption'!$D$13:$F$20,4,0)*$K12,0) -> 4000 | P12: =IFERROR(HLOOKUP($E12,'Returns & Asset Mix assumption'!$D$13:$F$20,5,0)*$K12,0) -> 0 | Q12: =IFERROR(HLOOKUP($E12,'Returns & Asset Mix assumption'!$D$13:$F$20,6,0)*$K12,0) -> 0 | R12: =IFERROR(HLOOKUP($E12,'Returns & Asset Mix assumption'!$D$13:$F$20,7,0)*$K12,0) -> 0
B13: FIRE Number | C13: 8 | D13: 20 | E13: =IF(ISBLANK(D13)=TRUE,"",IF(D13<3,"Short Term",IF(D13<=6,"Medium Term","Long Term"))) -> Long Term | F13: 7200000 | G13: 255000 | H13: 0.06 | I13: =IFERROR(IF(F13=G13," ",F13*(1+H13)^D13-G13*(1+HLOOKUP(E13,'Returns & Asset Mix assumption'!$D$13:$F$20,8,0))^D13),"") -> 20998124 | J13: 0.15 | K13: 7500 | M13: =IFERROR(HLOOKUP($E13,'Returns & Asset Mix assumption'!$D$13:$F$20,2,0)*$K13,0) -> 4500 | N13: =IFERROR(HLOOKUP($E13,'Returns & Asset Mix assumption'!$D$13:$F$20,3,0)*$K13,0) -> 750 | O13: =IFERROR(HLOOKUP($E13,'Returns & Asset Mix assumption'!$D$13:$F$20,4,0)*$K13,0) -> 1125 | P13: =IFERROR(HLOOKUP($E13,'Returns & Asset Mix assumption'!$D$13:$F$20,5,0)*$K13,0) -> 375 | Q13: =IFERROR(HLOOKUP($E13,'Returns & Asset Mix assumption'!$D$13:$F$20,6,0)*$K13,0) -> 375 | R13: =IFERROR(HLOOKUP($E13,'Returns & Asset Mix assumption'!$D$13:$F$20,7,0)*$K13,0) -> 375
B14: Buy Gold in Diwali | C14: 4 | D14: 1 | E14: =IF(ISBLANK(D14)=TRUE,"",IF(D14<3,"Short Term",IF(D14<=6,"Medium Term","Long Term"))) -> Short Term | F14: 130000 | G14: 0 | H14: 0.2 | I14: =IFERROR(IF(F14=G14," ",F14*(1+H14)^D14-G14*(1+HLOOKUP(E14,'Returns & Asset Mix assumption'!$D$13:$F$20,8,0))^D14),"") -> 156000 | J14: 0.1 | K14: 11000 | M14: =IFERROR(HLOOKUP($E14,'Returns & Asset Mix assumption'!$D$13:$F$20,2,0)*$K14,0) -> 0 | N14: =IFERROR(HLOOKUP($E14,'Returns & Asset Mix assumption'!$D$13:$F$20,3,0)*$K14,0) -> 0 | O14: =IFERROR(HLOOKUP($E14,'Returns & Asset Mix assumption'!$D$13:$F$20,4,0)*$K14,0) -> 11000 | P14: =IFERROR(HLOOKUP($E14,'Returns & Asset Mix assumption'!$D$13:$F$20,5,0)*$K14,0) -> 0 | Q14: =IFERROR(HLOOKUP($E14,'Returns & Asset Mix assumption'!$D$13:$F$20,6,0)*$K14,0) -> 0 | R14: =IFERROR(HLOOKUP($E14,'Returns & Asset Mix assumption'!$D$13:$F$20,7,0)*$K14,0) -> 0
B15: Buy Scooty for Wife | C15: 4 | D15: 1 | E15: =IF(ISBLANK(D15)=TRUE,"",IF(D15<3,"Short Term",IF(D15<=6,"Medium Term","Long Term"))) -> Short Term | F15: 120000 | G15: 0 | H15: 0.02 | I15: =IFERROR(IF(F15=G15," ",F15*(1+H15)^D15-G15*(1+HLOOKUP(E15,'Returns & Asset Mix assumption'!$D$13:$F$20,8,0))^D15),"") -> 122400 | J15: 0.05 | K15: 6000 | M15: =IFERROR(HLOOKUP($E15,'Returns & Asset Mix assumption'!$D$13:$F$20,2,0)*$K15,0) -> 0 | N15: =IFERROR(HLOOKUP($E15,'Returns & Asset Mix assumption'!$D$13:$F$20,3,0)*$K15,0) -> 0 | O15: =IFERROR(HLOOKUP($E15,'Returns & Asset Mix assumption'!$D$13:$F$20,4,0)*$K15,0) -> 6000 | P15: =IFERROR(HLOOKUP($E15,'Returns & Asset Mix assumption'!$D$13:$F$20,5,0)*$K15,0) -> 0 | Q15: =IFERROR(HLOOKUP($E15,'Returns & Asset Mix assumption'!$D$13:$F$20,6,0)*$K15,0) -> 0 | R15: =IFERROR(HLOOKUP($E15,'Returns & Asset Mix assumption'!$D$13:$F$20,7,0)*$K15,0) -> 0
B16: Ekansh 1st Birthday | C16: 2 | D16: 1 | E16: =IF(ISBLANK(D16)=TRUE,"",IF(D16<3,"Short Term",IF(D16<=6,"Medium Term","Long Term"))) -> Short Term | F16: 150000 | G16: 0 | H16: 0.01 | I16: =IFERROR(IF(F16=G16," ",F16*(1+H16)^D16-G16*(1+HLOOKUP(E16,'Returns & Asset Mix assumption'!$D$13:$F$20,8,0))^D16),"") -> 151500 | J16: 0.1 | K16: 6500 | M16: =IFERROR(HLOOKUP($E16,'Returns & Asset Mix assumption'!$D$13:$F$20,2,0)*$K16,0) -> 0 | N16: =IFERROR(HLOOKUP($E16,'Returns & Asset Mix assumption'!$D$13:$F$20,3,0)*$K16,0) -> 0 | O16: =IFERROR(HLOOKUP($E16,'Returns & Asset Mix assumption'!$D$13:$F$20,4,0)*$K16,0) -> 6500 | P16: =IFERROR(HLOOKUP($E16,'Returns & Asset Mix assumption'!$D$13:$F$20,5,0)*$K16,0) -> 0 | Q16: =IFERROR(HLOOKUP($E16,'Returns & Asset Mix assumption'!$D$13:$F$20,6,0)*$K16,0) -> 0 | R16: =IFERROR(HLOOKUP($E16,'Returns & Asset Mix assumption'!$D$13:$F$20,7,0)*$K16,0) -> 0
B17: Ekansh Education | C17: 4 | D17: 16 | E17: =IF(ISBLANK(D17)=TRUE,"",IF(D17<3,"Short Term",IF(D17<=6,"Medium Term","Long Term"))) -> Long Term | F17: 1500000 | G17: 0 | H17: 0.1 | I17: =IFERROR(IF(F17=G17," ",F17*(1+H17)^D17-G17*(1+HLOOKUP(E17,'Returns & Asset Mix assumption'!$D$13:$F$20,8,0))^D17),"") -> 6892459.5 | M17: =IFERROR(HLOOKUP($E17,'Returns & Asset Mix assumption'!$D$13:$F$20,2,0)*$K17,0) -> 0 | N17: =IFERROR(HLOOKUP($E17,'Returns & Asset Mix assumption'!$D$13:$F$20,3,0)*$K17,0) -> 0 | O17: =IFERROR(HLOOKUP($E17,'Returns & Asset Mix assumption'!$D$13:$F$20,4,0)*$K17,0) -> 0 | P17: =IFERROR(HLOOKUP($E17,'Returns & Asset Mix assumption'!$D$13:$F$20,5,0)*$K17,0) -> 0 | Q17: =IFERROR(HLOOKUP($E17,'Returns & Asset Mix assumption'!$D$13:$F$20,6,0)*$K17,0) -> 0 | R17: =IFERROR(HLOOKUP($E17,'Returns & Asset Mix assumption'!$D$13:$F$20,7,0)*$K17,0) -> 0
B18: Ekansh Marriage | C18: 6 | D18: 25 | E18: =IF(ISBLANK(D18)=TRUE,"",IF(D18<3,"Short Term",IF(D18<=6,"Medium Term","Long Term"))) -> Long Term | F18: 2000000 | G18: 0 | H18: 0.06 | I18: =IFERROR(IF(F18=G18," ",F18*(1+H18)^D18-G18*(1+HLOOKUP(E18,'Returns & Asset Mix assumption'!$D$13:$F$20,8,0))^D18),"") -> 8583741.4 | M18: =IFERROR(HLOOKUP($E18,'Returns & Asset Mix assumption'!$D$13:$F$20,2,0)*$K18,0) -> 0 | N18: =IFERROR(HLOOKUP($E18,'Returns & Asset Mix assumption'!$D$13:$F$20,3,0)*$K18,0) -> 0 | O18: =IFERROR(HLOOKUP($E18,'Returns & Asset Mix assumption'!$D$13:$F$20,4,0)*$K18,0) -> 0 | P18: =IFERROR(HLOOKUP($E18,'Returns & Asset Mix assumption'!$D$13:$F$20,5,0)*$K18,0) -> 0 | Q18: =IFERROR(HLOOKUP($E18,'Returns & Asset Mix assumption'!$D$13:$F$20,6,0)*$K18,0) -> 0 | R18: =IFERROR(HLOOKUP($E18,'Returns & Asset Mix assumption'!$D$13:$F$20,7,0)*$K18,0) -> 0
B19: Vacation Plan Yearly | C19: 6 | D19: 1 | E19: =IF(ISBLANK(D19)=TRUE,"",IF(D19<3,"Short Term",IF(D19<=6,"Medium Term","Long Term"))) -> Short Term | F19: 200000 | G19: 0 | H19: 0.1 | I19: =IFERROR(IF(F19=G19," ",F19*(1+H19)^D19-G19*(1+HLOOKUP(E19,'Returns & Asset Mix assumption'!$D$13:$F$20,8,0))^D19),"") -> 220000 | M19: =IFERROR(HLOOKUP($E19,'Returns & Asset Mix assumption'!$D$13:$F$20,2,0)*$K19,0) -> 0 | N19: =IFERROR(HLOOKUP($E19,'Returns & Asset Mix assumption'!$D$13:$F$20,3,0)*$K19,0) -> 0 | O19: =IFERROR(HLOOKUP($E19,'Returns & Asset Mix assumption'!$D$13:$F$20,4,0)*$K19,0) -> 0 | P19: =IFERROR(HLOOKUP($E19,'Returns & Asset Mix assumption'!$D$13:$F$20,5,0)*$K19,0) -> 0 | Q19: =IFERROR(HLOOKUP($E19,'Returns & Asset Mix assumption'!$D$13:$F$20,6,0)*$K19,0) -> 0 | R19: =IFERROR(HLOOKUP($E19,'Returns & Asset Mix assumption'!$D$13:$F$20,7,0)*$K19,0) -> 0
E20: =IF(ISBLANK(D20)=TRUE,"",IF(D20<3,"Short Term",IF(D20<=6,"Medium Term","Long Term"))) | I20: =IFERROR(IF(F20=G20," ",F20*(1+H20)^D20-G20*(1+HLOOKUP(E20,'Returns & Asset Mix assumption'!$D$13:$F$20,8,0))^D20),"") | M20: =IFERROR(HLOOKUP($E20,'Returns & Asset Mix assumption'!$D$13:$F$20,2,0)*$K20,0) -> 0 | N20: =IFERROR(HLOOKUP($E20,'Returns & Asset Mix assumption'!$D$13:$F$20,3,0)*$K20,0) -> 0 | O20: =IFERROR(HLOOKUP($E20,'Returns & Asset Mix assumption'!$D$13:$F$20,4,0)*$K20,0) -> 0 | P20: =IFERROR(HLOOKUP($E20,'Returns & Asset Mix assumption'!$D$13:$F$20,5,0)*$K20,0) -> 0 | Q20: =IFERROR(HLOOKUP($E20,'Returns & Asset Mix assumption'!$D$13:$F$20,6,0)*$K20,0) -> 0 | R20: =IFERROR(HLOOKUP($E20,'Returns & Asset Mix assumption'!$D$13:$F$20,7,0)*$K20,0) -> 0
E21: =IF(ISBLANK(D21)=TRUE,"",IF(D21<3,"Short Term",IF(D21<=6,"Medium Term","Long Term"))) | I21: =IFERROR(IF(F21=G21," ",F21*(1+H21)^D21-G21*(1+HLOOKUP(E21,'Returns & Asset Mix assumption'!$D$13:$F$20,8,0))^D21),"") | M21: =IFERROR(HLOOKUP($E21,'Returns & Asset Mix assumption'!$D$13:$F$20,2,0)*$K21,0) -> 0 | N21: =IFERROR(HLOOKUP($E21,'Returns & Asset Mix assumption'!$D$13:$F$20,3,0)*$K21,0) -> 0 | O21: =IFERROR(HLOOKUP($E21,'Returns & Asset Mix assumption'!$D$13:$F$20,4,0)*$K21,0) -> 0 | P21: =IFERROR(HLOOKUP($E21,'Returns & Asset Mix assumption'!$D$13:$F$20,5,0)*$K21,0) -> 0 | Q21: =IFERROR(HLOOKUP($E21,'Returns & Asset Mix assumption'!$D$13:$F$20,6,0)*$K21,0) -> 0 | R21: =IFERROR(HLOOKUP($E21,'Returns & Asset Mix assumption'!$D$13:$F$20,7,0)*$K21,0) -> 0
E22: =IF(ISBLANK(D22)=TRUE,"",IF(D22<3,"Short Term",IF(D22<=6,"Medium Term","Long Term"))) | I22: =IFERROR(IF(F22=G22," ",F22*(1+H22)^D22-G22*(1+HLOOKUP(E22,'Returns & Asset Mix assumption'!$D$13:$F$20,8,0))^D22),"") | M22: =IFERROR(HLOOKUP($E22,'Returns & Asset Mix assumption'!$D$13:$F$20,2,0)*$K22,0) -> 0 | N22: =IFERROR(HLOOKUP($E22,'Returns & Asset Mix assumption'!$D$13:$F$20,3,0)*$K22,0) -> 0 | O22: =IFERROR(HLOOKUP($E22,'Returns & Asset Mix assumption'!$D$13:$F$20,4,0)*$K22,0) -> 0 | P22: =IFERROR(HLOOKUP($E22,'Returns & Asset Mix assumption'!$D$13:$F$20,5,0)*$K22,0) -> 0 | Q22: =IFERROR(HLOOKUP($E22,'Returns & Asset Mix assumption'!$D$13:$F$20,6,0)*$K22,0) -> 0 | R22: =IFERROR(HLOOKUP($E22,'Returns & Asset Mix assumption'!$D$13:$F$20,7,0)*$K22,0) -> 0
E23: =IF(ISBLANK(D23)=TRUE,"",IF(D23<3,"Short Term",IF(D23<=6,"Medium Term","Long Term"))) | I23: =IFERROR(IF(F23=G23," ",F23*(1+H23)^D23-G23*(1+HLOOKUP(E23,'Returns & Asset Mix assumption'!$D$13:$F$20,8,0))^D23),"") | M23: =IFERROR(HLOOKUP($E23,'Returns & Asset Mix assumption'!$D$13:$F$20,2,0)*$K23,0) -> 0 | N23: =IFERROR(HLOOKUP($E23,'Returns & Asset Mix assumption'!$D$13:$F$20,3,0)*$K23,0) -> 0 | O23: =IFERROR(HLOOKUP($E23,'Returns & Asset Mix assumption'!$D$13:$F$20,4,0)*$K23,0) -> 0 | P23: =IFERROR(HLOOKUP($E23,'Returns & Asset Mix assumption'!$D$13:$F$20,5,0)*$K23,0) -> 0 | Q23: =IFERROR(HLOOKUP($E23,'Returns & Asset Mix assumption'!$D$13:$F$20,6,0)*$K23,0) -> 0 | R23: =IFERROR(HLOOKUP($E23,'Returns & Asset Mix assumption'!$D$13:$F$20,7,0)*$K23,0) -> 0
E24: =IF(ISBLANK(D24)=TRUE,"",IF(D24<3,"Short Term",IF(D24<=6,"Medium Term","Long Term"))) | I24: =IFERROR(IF(F24=G24," ",F24*(1+H24)^D24-G24*(1+HLOOKUP(E24,'Returns & Asset Mix assumption'!$D$13:$F$20,8,0))^D24),"") | M24: =IFERROR(HLOOKUP($E24,'Returns & Asset Mix assumption'!$D$13:$F$20,2,0)*$K24,0) -> 0 | N24: =IFERROR(HLOOKUP($E24,'Returns & Asset Mix assumption'!$D$13:$F$20,3,0)*$K24,0) -> 0 | O24: =IFERROR(HLOOKUP($E24,'Returns & Asset Mix assumption'!$D$13:$F$20,4,0)*$K24,0) -> 0 | P24: =IFERROR(HLOOKUP($E24,'Returns & Asset Mix assumption'!$D$13:$F$20,5,0)*$K24,0) -> 0 | Q24: =IFERROR(HLOOKUP($E24,'Returns & Asset Mix assumption'!$D$13:$F$20,6,0)*$K24,0) -> 0 | R24: =IFERROR(HLOOKUP($E24,'Returns & Asset Mix assumption'!$D$13:$F$20,7,0)*$K24,0) -> 0
E25: =IF(ISBLANK(D25)=TRUE,"",IF(D25<3,"Short Term",IF(D25<=6,"Medium Term","Long Term"))) | I25: =IFERROR(IF(F25=G25," ",F25*(1+H25)^D25-G25*(1+HLOOKUP(E25,'Returns & Asset Mix assumption'!$D$13:$F$20,8,0))^D25),"") | M25: =IFERROR(HLOOKUP($E25,'Returns & Asset Mix assumption'!$D$13:$F$20,2,0)*$K25,0) -> 0 | N25: =IFERROR(HLOOKUP($E25,'Returns & Asset Mix assumption'!$D$13:$F$20,3,0)*$K25,0) -> 0 | O25: =IFERROR(HLOOKUP($E25,'Returns & Asset Mix assumption'!$D$13:$F$20,4,0)*$K25,0) -> 0 | P25: =IFERROR(HLOOKUP($E25,'Returns & Asset Mix assumption'!$D$13:$F$20,5,0)*$K25,0) -> 0 | Q25: =IFERROR(HLOOKUP($E25,'Returns & Asset Mix assumption'!$D$13:$F$20,6,0)*$K25,0) -> 0 | R25: =IFERROR(HLOOKUP($E25,'Returns & Asset Mix assumption'!$D$13:$F$20,7,0)*$K25,0) -> 0
F27: Total | G27: =SUM(G11:G25) -> 542371 | J27: Total | K27: =SUM(K11:K25) -> 45000 | M27: =SUM(M11:M25) -> 4500 | N27: =SUM(N11:N25) -> 750 | O27: =SUM(O11:O25) -> 38625 | P27: =SUM(P11:P25) -> 375 | Q27: =SUM(Q11:Q25) -> 375 | R27: =SUM(R11:R25) -> 375
F28: Max | G28: ='Net worth'!C33+SUM('Net worth'!C18:C20)+'Net worth'!C16 -> 3645230 | J28: Max | K28: ='Cash flows'!C27 -> 17500 | M28: =M27/SUM($M$27:$R$27) -> 0.1 | N28: =N27/SUM($M$27:$R$27) -> 0.016666667 | O28: =O27/SUM($M$27:$R$27) -> 0.85833333 | P28: =P27/SUM($M$27:$R$27) -> 0.0083333333 | Q28: =Q27/SUM($M$27:$R$27) -> 0.0083333333 | R28: =R27/SUM($M$27:$R$27) -> 0.0083333333
F29: Available | G29: =G28-G27 -> 3102859 | J29: Available | K29: =K28-K27 -> -27500
G30: =IF(G27>G28,"You don't have enough money","") | K30: =IF(K27>'Cash flows'!C27,"You don't have enough money","") -> You don't have enough money
